egytech_fyi/__init__.py
egytech_fyi/core.py
egytech_fyi/models.py
egytech_fyi-0.1.35.dist-info/LICENSE
egytech_fyi-0.1.35.dist-info/METADATA
egytech_fyi-0.1.35.dist-info/WHEEL
egytech_fyi-0.1.35.dist-info/RECORD
