Metadata-Version: 2.1
Name: egytech_fyi
Version: 0.1.35
Summary: A Python API Wrapper for the EgyTech.FYI API
Author: Abdulrahman Mustafa Abdulrahman
Author-email: abdulrahman.m.khaled@outlook.com
Requires-Python: >=3.11,<4.0
Classifier: Programming Language :: Python :: 3
Classifier: Programming Language :: Python :: 3.11
Requires-Dist: httpx (>=0.27.0,<0.28.0)
Requires-Dist: pandas (>=2.1,<3.0)
Requires-Dist: pydantic (>=2.7.3,<3.0.0)
Requires-Dist: tomli (>=2.0.1,<3.0.0)
Requires-Dist: xlsxwriter (>=3.2.0,<4.0.0)
